[
 {
  "category": "it",
  "pub_date": "07-03-2025",
  "title": "Vi søger dygtig kollega til installationsteamet i Aalborg",
  "company": "AV CENTER Aalborg ApS",
  "location": "Nørresundby",
  "job_URL": "https://www.jobindex.dk/jobannonce/h1537660/vi-soeger-dygtig-kollega-til-installationsteamet-i-aalborg"
 },
 {
  "category": "it",
  "pub_date": "06-03-2025",
  "title": "Udviklingschef/CTO til Satlab A/S  - udvikling af radiosystemer til rumindustrien",
  "company": "Hedevang - Ledelse & Hr ApS",
  "location": "Aalborg Øst",
  "job_URL": "https://www.jobindex.dk/jobannonce/h1544283/udviklingschef-cto-til-satlab-a-s-udvikling-af-radiosystemer-til-rumindustrien"
 },
 {
  "category": "it",
  "pub_date": "06-03-2025",
  "title": "Software Specialist - Power Protections",
  "company": "DEIF A/S",
  "location": "Skive, Silkeborg, Odense eller Aalborg og mulighed for hjemmearbejde",
  "job_URL": "https://www.jobindex.dk/jobannonce/h1545566/software-specialist-power-protections"
 },
 {
  "category": "it",
  "pub_date": "06-03-2025",
  "title": "Software Architect",
  "company": "Roima Denmark Holding",
  "location": "Aalborg SV, Holte, Aarhus C eller København",
  "job_URL": "https://www.jobindex.dk/jobannonce/h1545351/software-architect"
 },
 {
  "category": "it",
  "pub_date": "06-03-2025",
  "title": "Manager til Quality Assurance - Tag kvaliteten til nye højder sammen med os",
  "company": "Norlys",
  "location": "Aalborg, Tranbjerg J eller København K",
  "job_URL": "https://www.job-karriere.dk/Norlys/job/Tranbjerg-Manager-til-Quality-Assurance-Tag-kvaliteten-til-nye-h%C3%B8jder-sammen-med-os-8310/1178465201/"
 },
 {
  "category": "it",
  "pub_date": "05-03-2025",
  "title": "Erfaren test manager til softwarevirksomhed",
  "company": "Admin By Request ApS",
  "location": "Aalborg",
  "job_URL": "https://www.jobindex.dk/jobannonce/h1545076/erfaren-test-manager-til-softwarevirksomhed"
 },
 {
  "category": "it",
  "pub_date": "05-03-2025",
  "title": "Junior Business Central Developer",
  "company": "Tasklet Factory ApS",
  "location": "Aalborg Øst",
  "job_URL": "https://www.jobindex.dk/jobannonce/h1544813/junior-business-central-developer"
 },
 {
  "category": "it",
  "pub_date": "05-03-2025",
  "title": "Erfaren Business Central Developer",
  "company": "Tasklet Factory ApS",
  "location": "Aalborg Øst",
  "job_URL": "https://www.jobindex.dk/jobannonce/h1544811/erfaren-business-central-developer"
 },
 {
  "category": "it",
  "pub_date": "05-03-2025",
  "title": "Senior Platform Engineer",
  "company": "Continia Software A/S",
  "location": "Copenhagen Ø or Nørresundby",
  "job_URL": "https://candidate.hr-manager.net/ApplicationInit.aspx?cid=2032&ProjectId=143677&DepartmentId=18974&MediaId=5"
 },
 {
  "category": "it",
  "pub_date": "05-03-2025",
  "title": "Projektingeniør – Nordjylland",
  "company": "Init Denmark A/S",
  "location": "Thisted, Aalborg SV eller Vrå",
  "job_URL": "https://init.career.emply.com/ad/projektingenior-nordjylland/xrpdyc"
 },
 {
  "category": "it",
  "pub_date": "05-03-2025",
  "title": "Driftsspecialist",
  "company": "KMD A/S",
  "location": "Aalborg",
  "job_URL": "https://jobs.kmd.net/default/job/Aalborg-Driftsspecialist-9000/1178243301/?utm_source=jobindex"
 },
 {
  "category": "it",
  "pub_date": "04-03-2025",
  "title": "Master Data Specialist",
  "company": "Wrist Ship Supply",
  "location": "Nørresundby",
  "job_URL": "https://www.jobindex.dk/jobannonce/h1544687/master-data-specialist"
 },
 {
  "category": "it",
  "pub_date": "04-03-2025",
  "title": "Backend Developer",
  "company": "MapsPeople A/S",
  "location": "Nørresundby",
  "job_URL": "https://mapspeople.career.emply.com/ad/backend-developer/ehwsgt/en"
 },
 {
  "category": "it",
  "pub_date": "04-03-2025",
  "title": "Senior Software Engineer",
  "company": "Continia Software A/S",
  "location": "København Ø or Nørresundby",
  "job_URL": "https://candidate.hr-manager.net/ApplicationInit.aspx?cid=2032&ProjectId=143676&DepartmentId=18956&MediaId=5"
 },
 {
  "category": "it",
  "pub_date": "03-03-2025",
  "title": "Intern IT-Konsulent",
  "company": "Arctic Import A/S",
  "location": "Aalborg Øst",
  "job_URL": "https://www.jobindex.dk/jobannonce/h1544235/intern-it-konsulent"
 },
 {
  "category": "it",
  "pub_date": "03-03-2025",
  "title": "Network Solution Architect",
  "company": "Telenor",
  "location": "Aalborg",
  "job_URL": "https://candidate.hr-manager.net/ApplicationInit.aspx?cid=1311&ProjectId=145880&DepartmentId=18957&MediaId=5"
 },
 {
  "category": "it",
  "pub_date": "03-03-2025",
  "title": "Projektleder – med NAV-/BC-erfaring",
  "company": "Nav-Vision ApS",
  "location": "Viborg eller Aalborg",
  "job_URL": "https://www.jobindex.dk/jobannonce/h1543874/projektleder-med-nav-bc-erfaring"
 },
 {
  "category": "it",
  "pub_date": "03-03-2025",
  "title": "Power Platform Konsulent",
  "company": "Nav-Vision ApS",
  "location": "Viborg eller Aalborg",
  "job_URL": "https://www.jobindex.dk/jobannonce/h1543871/power-platform-konsulent"
 },
 {
  "category": "it",
  "pub_date": "03-03-2025",
  "title": "Head of IT & Business Systems",
  "company": "Continia Software A/S",
  "location": "Copenhagen or Nørresundby",
  "job_URL": "https://candidate.hr-manager.net/ApplicationInit.aspx?cid=2032&ProjectId=143674&DepartmentId=18974&MediaId=5"
 },
 {
  "category": "industri",
  "pub_date": "07-03-2025",
  "title": "Project Engineer – Electrical Design",
  "company": "Körber Supply Chain DK A/S",
  "location": "Arden",
  "job_URL": "https://jobs.koerber.com/job/Arden-Project-Engineer-Electrical-Design/1169025401/"
 },
 {
  "category": "industri",
  "pub_date": "07-03-2025",
  "title": "Vi søger dygtig kollega til installationsteamet i Aalborg",
  "company": "AV CENTER Aalborg ApS",
  "location": "Nørresundby",
  "job_URL": "https://www.jobindex.dk/jobannonce/h1537660/vi-soeger-dygtig-kollega-til-installationsteamet-i-aalborg"
 },
 {
  "category": "industri",
  "pub_date": "06-03-2025",
  "title": "Er du vores nye procesoperatør til Food Oil i Agersted?",
  "company": "DLG",
  "location": "Dronninglund",
  "job_URL": "https://candidate.hr-manager.net/ApplicationInit.aspx?cid=363&ProjectId=189116&DepartmentId=15536&MediaId=5"
 },
 {
  "category": "industri",
  "pub_date": "06-03-2025",
  "title": "Sælgere til stor vindueskoncern i fremdrift",
  "company": "NorDan Vinduer A/S",
  "location": "Greve, Horsens eller Nordjylland",
  "job_URL": "https://www.jobindex.dk/jobannonce/h1544946/saelgere-til-stor-vindueskoncern-i-fremdrift"
 },
 {
  "category": "industri",
  "pub_date": "06-03-2025",
  "title": "Automation Engineer",
  "company": "DESMI Danmark A/S",
  "location": "Nørresundby",
  "job_URL": "https://job.desmi.com/REK/Joblist/Job.aspx?jobOfferInstanceId=4506&joblistId=1&lang=en"
 },
 {
  "category": "industri",
  "pub_date": "06-03-2025",
  "title": "VW Ekspert til Volkswagen Aalborg – En del af Semler Mobility",
  "company": "Semler Gruppen",
  "location": "Aalborg",
  "job_URL": "https://jobs.semler.dk/job/Aalborg-VW-Ekspert-til-Volkswagen-Aalborg-En-del-af-Semler-Mobility-9000/815212102/"
 },
 {
  "category": "industri",
  "pub_date": "06-03-2025",
  "title": "Lagermedarbejder",
  "company": "Trinol A/S",
  "location": "Nørresundby, Hobro",
  "job_URL": "https://trinol.dk/karriere/job-detalje?jobId=145098"
 },
 {
  "category": "industri",
  "pub_date": "06-03-2025",
  "title": "Vi søger rejsemontører til Kongsberg!",
  "company": "Temp-Team A/S",
  "location": "Aalborg Øst og mulighed for hjemmearbejde",
  "job_URL": "https://temp-team.dk/job-search/vi-soger-rejsemontorer-til-kongsberg-420495"
 },
 {
  "category": "industri",
  "pub_date": "06-03-2025",
  "title": "Industrielektriker / automatiktekniker",
  "company": "Tetra Pak Inventing A/S",
  "location": "Hjørring",
  "job_URL": "https://www.jobindex.dk/jobannonce/h1545363/industrielektriker-automatiktekniker"
 },
 {
  "category": "industri",
  "pub_date": "06-03-2025",
  "title": "Værkfører Volvo Truck Center Aalborg",
  "company": "Volvo Truck Center Danmark A/S",
  "location": "Aalborg Øst",
  "job_URL": "https://www.jobindex.dk/jobannonce/h1545354/vaerkfoerer-volvo-truck-center-aalborg"
 },
 {
  "category": "industri",
  "pub_date": "05-03-2025",
  "title": "Erfaren Automationsingeniør til vores Automationsafdeling i Aalborg",
  "company": "CBRE Teknisk Servicepartner",
  "location": "Aalborg",
  "job_URL": "https://www.jobindex.dk/jobannonce/h1545206/erfaren-automationsingenioer-til-vores-automationsafdeling-i-aalborg"
 },
 {
  "category": "industri",
  "pub_date": "05-03-2025",
  "title": "El-konstruktør med erfaring indenfor El og Automation til Aalborg",
  "company": "CBRE Teknisk Servicepartner",
  "location": "Aalborg",
  "job_URL": "https://www.jobindex.dk/jobannonce/h1545205/el-konstruktoer-med-erfaring-indenfor-el-og-automation-til-aalborg"
 },
 {
  "category": "handel",
  "pub_date": "28-02-2025",
  "title": "Peopleorienteret Butikschef til Telenor i Hjørring",
  "company": "Telenor",
  "location": "Hjørring",
  "job_URL": "https://candidate.hr-manager.net/ApplicationInit.aspx?cid=1311&ProjectId=145877&DepartmentId=18958&MediaId=5"
 },
 {
  "category": "handel",
  "pub_date": "06-03-2025",
  "title": "Butikschef - Fuldtid - Hobro",
  "company": "Lidl Danmark K/S",
  "location": "Hobro",
  "job_URL": "https://karriere.lidl.dk/jobs/butikschef-fuldtid-hobro-hobro-522979"
 },
 {
  "category": "handel",
  "pub_date": "06-03-2025",
  "title": "Vinduespudser til Feriepartner Thy",
  "company": "Feriepartner",
  "location": "Nr. Vorupør",
  "job_URL": "https://candidate.hr-manager.net/ApplicationInit.aspx?cid=2223&ProjectId=144969&DepartmentId=19280&MediaId=4631"
 },
 {
  "category": "handel",
  "pub_date": "06-03-2025",
  "title": "Indretningsarkitekt med passion for eksklusive kundeoplevelser",
  "company": "Svane Køkkenet",
  "location": "Aalborg SV",
  "job_URL": "https://www.jobindex.dk/img/pdf/stilling_indretningsarkitekt_aalborg-7.pdf"
 },
 {
  "category": "handel",
  "pub_date": "06-03-2025",
  "title": "Optometrist til Louis Nielsen Frederikshavn",
  "company": "Louis Nielsen A/S",
  "location": "Frederikshavn",
  "job_URL": "https://join.specsavers.com/louis-nielsen/position/optometrist-til-louis-nielsen-frederikshavn/"
 },
 {
  "category": "handel",
  "pub_date": "05-03-2025",
  "title": "Handelstrainee med speciale i salg",
  "company": "Carl Ras A/S",
  "location": "Aalborg",
  "job_URL": "https://app.jobmatchprofile.com/6ye57d/carl-ras-as/75chpd/handelstrainee-med-speciale-i-salg"
 },
 {
  "category": "handel",
  "pub_date": "05-03-2025",
  "title": "Kantineassistent",
  "company": "Marel A/S",
  "location": "Støvring",
  "job_URL": "https://marel.wd3.myworkdayjobs.com/da-DK/Marel/details/Kantineassistent_18698?source=jobindex_dk"
 },
 {
  "category": "handel",
  "pub_date": "05-03-2025",
  "title": "Bliv salgsassistent",
  "company": "Louis Nielsen A/S",
  "location": "Brønderslev",
  "job_URL": "https://www.jobindex.dk/jobannonce/reportage/2298/assistent-til-louis-nielsen-broenderselv"
 },
 {
  "category": "handel",
  "pub_date": "04-03-2025",
  "title": "Optometrist til Louis Nielsen Aalborg",
  "company": "Louis Nielsen A/S",
  "location": "Aalborg",
  "job_URL": "https://join.specsavers.com/louis-nielsen/position/optometrist-til-louis-nielsen-aalborg/"
 },
 {
  "category": "handel",
  "pub_date": "04-03-2025",
  "title": "Bliv salgsassistent",
  "company": "Louis Nielsen A/S",
  "location": "Aalborg",
  "job_URL": "https://www.jobindex.dk/jobannonce/reportage/2297/assistent-til-louis-nielsen-aalborg"
 },
 {
  "category": "handel",
  "pub_date": "04-03-2025",
  "title": "Delikatesseleder, Brugsen Tranum",
  "company": "Brugsen",
  "location": "Brovst",
  "job_URL": "https://jobs.coop.dk/job/Delikatesseleder%2C-Brugsen-Tranum/154683-da_DK"
 },
 {
  "category": "handel",
  "pub_date": "04-03-2025",
  "title": "Uddeler, BRF Brugsen Øster Hornum",
  "company": "Brugsen",
  "location": "Støvring",
  "job_URL": "https://jobs.coop.dk/job/Uddeler%2C-BRF-Brugsen-%C3%98ster-Hornum/154642-da_DK"
 },
 {
  "category": "handel",
  "pub_date": "03-03-2025",
  "title": "Sælger til Byggecenter/Malerafdeling i Nykøbing",
  "company": "XL-BYG",
  "location": "Nykøbing M",
  "job_URL": "https://app.elvium.com/da/positions/29610/job_posting?referer_host=www.jobindex.dk"
 },
 {
  "category": "handel",
  "pub_date": "03-03-2025",
  "title": "Store Manager til JYSK Skagen",
  "company": "JYSK",
  "location": "Skagen",
  "job_URL": "https://jobs.smartrecruiters.com/JYSK/744000045600550-store-manager-til-jysk-skagen?trid=9c834889-bbb7-437c-a553-3bcb9710b121"
 },
 {
  "category": "handel",
  "pub_date": "03-03-2025",
  "title": "Vil du være med til at uddanne fremtidens kosmetikere?",
  "company": "TECHCOLLEGE",
  "location": "Aalborg",
  "job_URL": "https://www.innomate.com/InnomatePublicPagesMedarb/JobNotice.aspx?CompanyId=tcaa&JobNoticeId=1045"
 },
 {
  "category": "handel",
  "pub_date": "03-03-2025",
  "title": "Køkkenchef/køkkenleder til kantinen hos Aalborg Politi",
  "company": "Coor Service Management A/S",
  "location": "Aalborg",
  "job_URL": "https://coor.easycruit.com/vacancy/3472037/239029?iso=dk"
 },
 {
  "category": "ledelse",
  "pub_date": "07-03-2025",
  "title": "Teknisk projektleder",
  "company": "idoc A/S",
  "location": "Vejle, Aalborg eller Albertslund",
  "job_URL": "https://www.jobindex.dk/jobannonce/h1528809/teknisk-projektleder"
 },
 {
  "category": "ledelse",
  "pub_date": "06-03-2025",
  "title": "Butikschef - Fuldtid - Hobro",
  "company": "Lidl Danmark K/S",
  "location": "Hobro",
  "job_URL": "https://karriere.lidl.dk/jobs/butikschef-fuldtid-hobro-hobro-522979"
 },
 {
  "category": "ledelse",
  "pub_date": "06-03-2025",
  "title": "PTD-PTU Chef - NØRAGER MEJERI",
  "company": "NORDEX FOOD A/S",
  "location": "Nørager",
  "job_URL": "https://candidate.hr-manager.net/ApplicationInit.aspx?cid=2382&ProjectId=143689&DepartmentId=18961&MediaId=5"
 },
 {
  "category": "ledelse",
  "pub_date": "06-03-2025",
  "title": "Afdelingschef for Support Erhverv Himmerland",
  "company": "Sparekassen Danmark",
  "location": "Aars eller Viborg",
  "job_URL": "https://www.jobindex.dk/jobannonce/h1545222/afdelingschef-for-support-erhverv-himmerland"
 },
 {
  "category": "ledelse",
  "pub_date": "06-03-2025",
  "title": "Udviklingschef/CTO til Satlab A/S  - udvikling af radiosystemer til rumindustrien",
  "company": "Hedevang - Ledelse & Hr ApS",
  "location": "Aalborg Øst",
  "job_URL": "https://www.jobindex.dk/jobannonce/h1544283/udviklingschef-cto-til-satlab-a-s-udvikling-af-radiosystemer-til-rumindustrien"
 },
 {
  "category": "ledelse",
  "pub_date": "06-03-2025",
  "title": "Graduate program",
  "company": "Eurowind Energy A/S",
  "location": "Hobro",
  "job_URL": "https://eurowindenergy.com/uk/career?hr=show-job/233830&locale=en_US#hrskyen"
 },
 {
  "category": "ledelse",
  "pub_date": "06-03-2025",
  "title": "Software Architect",
  "company": "Roima Denmark Holding",
  "location": "Aalborg SV, Holte, Aarhus C eller København",
  "job_URL": "https://www.jobindex.dk/jobannonce/h1545351/software-architect"
 },
 {
  "category": "ledelse",
  "pub_date": "06-03-2025",
  "title": "Manager til Quality Assurance - Tag kvaliteten til nye højder sammen med os",
  "company": "Norlys",
  "location": "Aalborg, Tranbjerg J eller København K",
  "job_URL": "https://www.job-karriere.dk/Norlys/job/Tranbjerg-Manager-til-Quality-Assurance-Tag-kvaliteten-til-nye-h%C3%B8jder-sammen-med-os-8310/1178465201/"
 },
 {
  "category": "ledelse",
  "pub_date": "05-03-2025",
  "title": "Finance Manager til BILA Group",
  "company": "BILA A/S",
  "location": "Nykøbing M",
  "job_URL": "https://candidate.hr-manager.net/ApplicationInit.aspx?cid=1523&ProjectId=144278&DepartmentId=18957&MediaId=4614"
 },
 {
  "category": "ledelse",
  "pub_date": "05-03-2025",
  "title": "Udviklingskonsulent til Drift og Anlæg",
  "company": "THISTED KOMMUNE",
  "location": "Hurup",
  "job_URL": "https://portal.signatur.dk/ExtJobs/DefaultHosting/JobDetails.aspx?ClientId=1546&WebAdId=135985"
 },
 {
  "category": "ledelse",
  "pub_date": "05-03-2025",
  "title": "Økonomichef",
  "company": "Hansen Toft A/S",
  "location": "Sæby",
  "job_URL": "https://www.hansentoft.dk/job/8851"
 },
 {
  "category": "ledelse",
  "pub_date": "04-03-2025",
  "title": "Head of Operations",
  "company": "Aalborg Energie Technik a/s",
  "location": "Aalborg Øst",
  "job_URL": "https://aet.2prec.com/vacancy/67c6cb1a3db99017dc4fbf30"
 },
 {
  "category": "ledelse",
  "pub_date": "04-03-2025",
  "title": "Markedsdirektør Private Banking Nord",
  "company": "Jyske Bank",
  "location": "Aalborg",
  "job_URL": "https://www.jyskebank.dk/om-os/job-og-karriere/job/jobopslag?id=190726"
 },
 {
  "category": "undervisning",
  "pub_date": "28-02-2025",
  "title": "Erfaren prøvesagkyndig eller kørelærer til videreudvikling af digitale teoriprøver",
  "company": "Færdselsstyrelsen",
  "location": "Kolding",
  "job_URL": "https://candidate.hr-manager.net/ApplicationInit.aspx?cid=5001&ProjectId=186986&DepartmentId=10047&MediaId=3396"
 },
 {
  "category": "undervisning",
  "pub_date": "28-02-2025",
  "title": "Altiden Knivholtvej søger en faglig stærk og erfaren socialpædagog",
  "company": "Altiden",
  "location": "Frederikshavn",
  "job_URL": "https://jobs.altiden.dk/jobs/5069262-altiden-knivholtvej-soeger-en-faglig-staerk-og-erfaren-socialpaedagog?promotion=1362362-jobindex"
 },
 {
  "category": "undervisning",
  "pub_date": "28-02-2025",
  "title": "Er du vores barselsvikar i biologi, matematik og idræt ved Astrup-Sønderskov Friskole",
  "company": "Astrup-Sønderskov Friskole",
  "location": "Hjørring",
  "job_URL": "https://www.jobindex.dk/jobannonce/h1543479/er-du-vores-barselsvikar-i-biologi-matematik-og-idraet-ved-astrup-soenderskov-friskole"
 },
 {
  "category": "undervisning",
  "pub_date": "28-02-2025",
  "title": "FGU Vendsyssels direktør går på pension den 1. august 2025, og derfor søger vi hendes afløser",
  "company": "FGU Vendsyssel",
  "location": "Hjørring",
  "job_URL": "https://www.jobindex.dk/jobannonce/h1543000/fgu-vendsyssels-direktoer-gaar-paa-pension-den-1-august-2025-og-derfor-soeger-vi-hendes-afloeser"
 },
 {
  "category": "undervisning",
  "pub_date": "27-02-2025",
  "title": "Energisk pædagogmedhjælper til privat daginstitution i Aalborg med fokus på udeliv, mad og økologi søges….",
  "company": "Daginstitutionen Troldehulen ApS",
  "location": "Aalborg",
  "job_URL": "https://www.jobindex.dk/jobannonce/h1543382/energisk-paedagogmedhjaelper-til-privat-daginstitution-i-aalborg-med-fokus-paa-udeliv-mad-og-oekologi-soeges"
 },
 {
  "category": "undervisning",
  "pub_date": "26-02-2025",
  "title": "Altiden Vester Hjermitslev søger en pædagogisk medarbejder med psykiatri-erfaring",
  "company": "Altiden",
  "location": "Brønderslev",
  "job_URL": "https://jobs.altiden.dk/jobs/5267251-altiden-vester-hjermitslev-soeger-en-paedagogisk-medarbejder-med-psykiatri-erfaring?promotion=1359092-jobindex"
 },
 {
  "category": "undervisning",
  "pub_date": "25-02-2025",
  "title": "Techcollege Mad og Oplevelser søger faglærer til tjeneruddannelsen",
  "company": "TECHCOLLEGE",
  "location": "Aalborg",
  "job_URL": "https://www.innomate.com/InnomatePublicPagesMedarb/JobNotice.aspx?CompanyId=tcaa&JobNoticeId=1043"
 },
 {
  "category": "undervisning",
  "pub_date": "21-02-2025",
  "title": "Pædagogisk assistent til Hannæs Børnehus",
  "company": "THISTED KOMMUNE",
  "location": "Frøstrup",
  "job_URL": "https://portal.signatur.dk/ExtJobs/DefaultHosting/JobDetails.aspx?ClientId=1546&WebAdId=135362"
 },
 {
  "category": "undervisning",
  "pub_date": "20-02-2025",
  "title": "Afdelingsleder til Handicapområdet - genopslag",
  "company": "Brønderslev Kommune",
  "location": "Brønderslev",
  "job_URL": "https://bronderslev-v2.career.emply.com/ad/afdelingsleder-til-handicapomradet-genopslag/mh2it5/da"
 },
 {
  "category": "undervisning",
  "pub_date": "18-02-2025",
  "title": "Research support to the oyster hatchery - DTU Aqua",
  "company": "DTU, Danmarks Tekniske Universitet",
  "location": "Nykøbing M",
  "job_URL": "https://efzu.fa.em2.oraclecloud.com/hcmUI/CandidateExperience/da/sites/CX_1/job/4693"
 },
 {
  "category": "undervisning",
  "pub_date": "17-02-2025",
  "title": "Skoleleder",
  "company": "Aalborg Friskole",
  "location": "Aalborg",
  "job_URL": "https://www.jobindex.dk/jobannonce/h1540228/skoleleder"
 },
 {
  "category": "undervisning",
  "pub_date": "06-03-2025",
  "title": "HabitusHusene Sct. Mortensgaard søger vågen nattevagt til vores solisttilbud",
  "company": "Habitus",
  "location": "Snedsted",
  "job_URL": "https://habitus.career.emply.com/ad/habitushusene-sct-mortensgaard-soger-vagen-nattevagt-til-vores-solisttilbud/i38ebn/da"
 },
 {
  "category": "undervisning",
  "pub_date": "04-03-2025",
  "title": "Lærer",
  "company": "Hørby Efterskole",
  "location": "Sæby",
  "job_URL": "https://www.jobindex.dk/jobannonce/h1544353/laerer"
 },
 {
  "category": "undervisning",
  "pub_date": "03-03-2025",
  "title": "Faglærer til vores økologiske landbrug",
  "company": "Fonden Nr. Vesterskov",
  "location": "Dybvad",
  "job_URL": "https://www.jobindex.dk/jobannonce/h1544031/faglaerer-til-vores-oekologiske-landbrug"
 },
 {
  "category": "undervisning",
  "pub_date": "03-03-2025",
  "title": "Vil du være med til at uddanne fremtidens kosmetikere?",
  "company": "TECHCOLLEGE",
  "location": "Aalborg",
  "job_URL": "https://www.innomate.com/InnomatePublicPagesMedarb/JobNotice.aspx?CompanyId=tcaa&JobNoticeId=1045"
 },
 {
  "category": "undervisning",
  "pub_date": "03-03-2025",
  "title": "Pædagogmedhjælper til Sjørring børnehus",
  "company": "THISTED KOMMUNE",
  "location": "Thisted",
  "job_URL": "https://portal.signatur.dk/ExtJobs/DefaultHosting/JobDetails.aspx?ClientId=1546&WebAdId=135772"
 },
 {
  "category": "undervisning",
  "pub_date": "03-03-2025",
  "title": "Pædagog til Sjørring børnehus",
  "company": "THISTED KOMMUNE",
  "location": "Thisted",
  "job_URL": "https://portal.signatur.dk/ExtJobs/DefaultHosting/JobDetails.aspx?ClientId=1546&WebAdId=135770"
 },
 {
  "category": "undervisning",
  "pub_date": "03-03-2025",
  "title": "Forretningsudvikler til spændende forskerpark",
  "company": "Curia",
  "location": "Hirtshals",
  "job_URL": "https://www.curia.dk/ledige-stillinger?jobid=22293&locale=da_DK"
 },
 {
  "category": "social",
  "pub_date": "28-02-2025",
  "title": "Altiden Knivholtvej søger en faglig stærk og erfaren socialpædagog",
  "company": "Altiden",
  "location": "Frederikshavn",
  "job_URL": "https://jobs.altiden.dk/jobs/5069262-altiden-knivholtvej-soeger-en-faglig-staerk-og-erfaren-socialpaedagog?promotion=1362362-jobindex"
 },
 {
  "category": "social",
  "pub_date": "28-02-2025",
  "title": "Erhvervspsykolog til HR Arbejdsmiljø - barselsvikariat",
  "company": "THISTED KOMMUNE",
  "location": "Thisted",
  "job_URL": "https://portal.signatur.dk/ExtJobs/DefaultHosting/JobDetails.aspx?ClientId=1546&WebAdId=135736"
 },
 {
  "category": "social",
  "pub_date": "27-02-2025",
  "title": "Psykolog til børne- og ungeområdet i Det Nationale Sorgcenter i Aalborg",
  "company": "Det Nationale Sorgcenter",
  "location": "Aalborg",
  "job_URL": "https://sorgcenter.career.emply.com/ad/psykolog-til-borne-og-ungeomradet-i-det-nationale-sorgcenter-i-aalborg/4wy7rk/da"
 },
 {
  "category": "social",
  "pub_date": "26-02-2025",
  "title": "Eventmanager ved InterForce Region Nordjylland",
  "company": "Forsvaret",
  "location": "Frederikshavn",
  "job_URL": "https://candidate.hr-manager.net/ApplicationInit.aspx?cid=3010&ProjectId=144598&DepartmentId=19301&MediaId=4735"
 },
 {
  "category": "social",
  "pub_date": "26-02-2025",
  "title": "Projektleder til driftsudbud",
  "company": "Forsvarsministeriets Ejendomsstyrelse",
  "location": "Hjørring",
  "job_URL": "https://candidate.hr-manager.net/ApplicationInit.aspx?cid=3010&ProjectId=144065&DepartmentId=19442&MediaId=4735"
 },
 {
  "category": "social",
  "pub_date": "06-03-2025",
  "title": "HabitusHusene Sct. Mortensgaard søger vågen nattevagt til vores solisttilbud",
  "company": "Habitus",
  "location": "Snedsted",
  "job_URL": "https://habitus.career.emply.com/ad/habitushusene-sct-mortensgaard-soger-vagen-nattevagt-til-vores-solisttilbud/i38ebn/da"
 },
 {
  "category": "social",
  "pub_date": "06-03-2025",
  "title": "Lægeklinikken Aars søger lægesekretær, farmakonom eller SOSA pr. 1.5.2025",
  "company": "Lægeklinikken Aars I/S",
  "location": "Aars",
  "job_URL": "https://www.jobindex.dk/jobannonce/h1545583/laegeklinikken-aars-soeger-laegesekretaer-farmakonom-eller-sosa-pr-152025"
 },
 {
  "category": "social",
  "pub_date": "06-03-2025",
  "title": "Optometrist til Louis Nielsen Frederikshavn",
  "company": "Louis Nielsen A/S",
  "location": "Frederikshavn",
  "job_URL": "https://join.specsavers.com/louis-nielsen/position/optometrist-til-louis-nielsen-frederikshavn/"
 },
 {
  "category": "social",
  "pub_date": "05-03-2025",
  "title": "Bidrag til at implementere ældrereformen – BDO Advisory søger konsulenter med fokus på kvalitet, udvikling og optimering",
  "company": "BDO",
  "location": "København, Aalborg, Odense eller Aarhus C",
  "job_URL": "https://jobs.bdo.dk/ad/bidrag-til-at-implementere-aeldrereformen-bdo-advisory-soger-konsulenter-med-fok/cgikwr"
 },
 {
  "category": "social",
  "pub_date": "05-03-2025",
  "title": "Koordinerende sagsbehandler til Team Ydelse, Job og Ressourcer og KUI Jobcenter",
  "company": "THISTED KOMMUNE",
  "location": "Thisted",
  "job_URL": "https://portal.signatur.dk/ExtJobs/DefaultHosting/JobDetails.aspx?ClientId=1546&WebAdId=135920"
 },
 {
  "category": "social",
  "pub_date": "04-03-2025",
  "title": "Teamleder med talent for planlægning",
  "company": "Mental Care ApS",
  "location": "Aalborg",
  "job_URL": "https://www.jobindex.dk/jobannonce/h1544334/teamleder-med-talent-for-planlaegning"
 },
 {
  "category": "social",
  "pub_date": "04-03-2025",
  "title": "Børne- og ungerådgivere til Børne- og familierådgivningen",
  "company": "THISTED KOMMUNE",
  "location": "Thisted",
  "job_URL": "https://portal.signatur.dk/ExtJobs/DefaultHosting/JobDetails.aspx?ClientId=1546&WebAdId=135899"
 },
 {
  "category": "social",
  "pub_date": "04-03-2025",
  "title": "Optometrist til Louis Nielsen Aalborg",
  "company": "Louis Nielsen A/S",
  "location": "Aalborg",
  "job_URL": "https://join.specsavers.com/louis-nielsen/position/optometrist-til-louis-nielsen-aalborg/"
 },
 {
  "category": "social",
  "pub_date": "04-03-2025",
  "title": "SSA i nattevagt til Hjemmeplejen Nord",
  "company": "THISTED KOMMUNE",
  "location": "Thisted",
  "job_URL": "https://portal.signatur.dk/ExtJobs/DefaultHosting/JobDetails.aspx?ClientId=1546&WebAdId=135851"
 },
 {
  "category": "social",
  "pub_date": "04-03-2025",
  "title": "Sommerferieafløsere til hjemmeplejen i Team Sydthy",
  "company": "THISTED KOMMUNE",
  "location": "Hurup Thy",
  "job_URL": "https://portal.signatur.dk/ExtJobs/DefaultHosting/JobDetails.aspx?ClientId=1546&WebAdId=135852"
 },
 {
  "category": "ingenioer",
  "pub_date": "07-03-2025",
  "title": "Project Engineer – Electrical Design",
  "company": "Körber Supply Chain DK A/S",
  "location": "Arden",
  "job_URL": "https://jobs.koerber.com/job/Arden-Project-Engineer-Electrical-Design/1169025401/"
 },
 {
  "category": "ingenioer",
  "pub_date": "07-03-2025",
  "title": "Teknisk projektleder",
  "company": "idoc A/S",
  "location": "Vejle, Aalborg eller Albertslund",
  "job_URL": "https://www.jobindex.dk/jobannonce/h1528809/teknisk-projektleder"
 },
 {
  "category": "ingenioer",
  "pub_date": "06-03-2025",
  "title": "PTD-PTU Chef - NØRAGER MEJERI",
  "company": "NORDEX FOOD A/S",
  "location": "Nørager",
  "job_URL": "https://candidate.hr-manager.net/ApplicationInit.aspx?cid=2382&ProjectId=143689&DepartmentId=18961&MediaId=5"
 },
 {
  "category": "ingenioer",
  "pub_date": "06-03-2025",
  "title": "Er du vores nye procesoperatør til Food Oil i Agersted?",
  "company": "DLG",
  "location": "Dronninglund",
  "job_URL": "https://candidate.hr-manager.net/ApplicationInit.aspx?cid=363&ProjectId=189116&DepartmentId=15536&MediaId=5"
 },
 {
  "category": "ingenioer",
  "pub_date": "06-03-2025",
  "title": "Udviklingschef/CTO til Satlab A/S  - udvikling af radiosystemer til rumindustrien",
  "company": "Hedevang - Ledelse & Hr ApS",
  "location": "Aalborg Øst",
  "job_URL": "https://www.jobindex.dk/jobannonce/h1544283/udviklingschef-cto-til-satlab-a-s-udvikling-af-radiosystemer-til-rumindustrien"
 },
 {
  "category": "ingenioer",
  "pub_date": "06-03-2025",
  "title": "Automation Engineer",
  "company": "DESMI Danmark A/S",
  "location": "Nørresundby",
  "job_URL": "https://job.desmi.com/REK/Joblist/Job.aspx?jobOfferInstanceId=4506&joblistId=1&lang=en"
 },
 {
  "category": "ingenioer",
  "pub_date": "06-03-2025",
  "title": "Maskinkonstruktør",
  "company": "idoc A/S",
  "location": "Vejle, Aalborg eller Albertslund",
  "job_URL": "https://www.jobindex.dk/jobannonce/h1528811/maskinkonstruktoer"
 },
 {
  "category": "ingenioer",
  "pub_date": "06-03-2025",
  "title": "Lægeklinikken Aars søger lægesekretær, farmakonom eller SOSA pr. 1.5.2025",
  "company": "Lægeklinikken Aars I/S",
  "location": "Aars",
  "job_URL": "https://www.jobindex.dk/jobannonce/h1545583/laegeklinikken-aars-soeger-laegesekretaer-farmakonom-eller-sosa-pr-152025"
 },
 {
  "category": "ingenioer",
  "pub_date": "06-03-2025",
  "title": "Software Specialist - Power Protections",
  "company": "DEIF A/S",
  "location": "Skive, Silkeborg, Odense eller Aalborg og mulighed for hjemmearbejde",
  "job_URL": "https://www.jobindex.dk/jobannonce/h1545566/software-specialist-power-protections"
 },
 {
  "category": "ingenioer",
  "pub_date": "06-03-2025",
  "title": "Quality Process Specialist",
  "company": "SVANEHØJ Danmark A/S",
  "location": "Svenstrup",
  "job_URL": "https://job.reqruiting.com/job.aspx?id=23087"
 },
 {
  "category": "ingenioer",
  "pub_date": "06-03-2025",
  "title": "Vi søger rejsemontører til Kongsberg!",
  "company": "Temp-Team A/S",
  "location": "Aalborg Øst og mulighed for hjemmearbejde",
  "job_URL": "https://temp-team.dk/job-search/vi-soger-rejsemontorer-til-kongsberg-420495"
 },
 {
  "category": "ingenioer",
  "pub_date": "05-03-2025",
  "title": "Erfaren Automationsingeniør til vores Automationsafdeling i Aalborg",
  "company": "CBRE Teknisk Servicepartner",
  "location": "Aalborg",
  "job_URL": "https://www.jobindex.dk/jobannonce/h1545206/erfaren-automationsingenioer-til-vores-automationsafdeling-i-aalborg"
 },
 {
  "category": "ingenioer",
  "pub_date": "05-03-2025",
  "title": "El-konstruktør med erfaring indenfor El og Automation til Aalborg",
  "company": "CBRE Teknisk Servicepartner",
  "location": "Aalborg",
  "job_URL": "https://www.jobindex.dk/jobannonce/h1545205/el-konstruktoer-med-erfaring-indenfor-el-og-automation-til-aalborg"
 },
 {
  "category": "ingenioer",
  "pub_date": "05-03-2025",
  "title": "Nyuddannet landinspektør til myndighedsteam",
  "company": "Vejdirektoratet",
  "location": "Aalborg Øst",
  "job_URL": "https://candidate.hr-manager.net/ApplicationInit.aspx?cid=5001&ProjectId=187102&DepartmentId=9790&MediaId=5"
 },
 {
  "category": "salg",
  "pub_date": "07-03-2025",
  "title": "Landets bedste kollega søges",
  "company": "Storm Group",
  "location": "Herning, Aalborg, Aarhus, Viborg, Kolding, Odense, Roskilde, Næstved, Hillerød eller København",
  "job_URL": "https://www.jobindex.dk/jobannonce/h1481700/landets-bedste-kollega-soeges"
 },
 {
  "category": "salg",
  "pub_date": "06-03-2025",
  "title": "Intern salgsmedarbejder til IBF i Nørresundby",
  "company": "A/S Ikast Betonvarefabrik (IBF)",
  "location": "Nørresundby",
  "job_URL": "https://ibf.career.emply.com/ad/intern-salgsmedarbejder-til-ibf-i-norresundby/ae93qx/da"
 },
 {
  "category": "salg",
  "pub_date": "06-03-2025",
  "title": "Indretningsarkitekt med passion for eksklusive kundeoplevelser",
  "company": "Svane Køkkenet",
  "location": "Aalborg SV",
  "job_URL": "https://www.jobindex.dk/img/pdf/stilling_indretningsarkitekt_aalborg-7.pdf"
 },
 {
  "category": "salg",
  "pub_date": "06-03-2025",
  "title": "Sælgere til stor vindueskoncern i fremdrift",
  "company": "NorDan Vinduer A/S",
  "location": "Greve, Horsens eller Nordjylland",
  "job_URL": "https://www.jobindex.dk/jobannonce/h1544946/saelgere-til-stor-vindueskoncern-i-fremdrift"
 },
 {
  "category": "salg",
  "pub_date": "06-03-2025",
  "title": "VW Ekspert til Volkswagen Aalborg – En del af Semler Mobility",
  "company": "Semler Gruppen",
  "location": "Aalborg",
  "job_URL": "https://jobs.semler.dk/job/Aalborg-VW-Ekspert-til-Volkswagen-Aalborg-En-del-af-Semler-Mobility-9000/815212102/"
 },
 {
  "category": "salg",
  "pub_date": "05-03-2025",
  "title": "Mødebooker",
  "company": "Forest & Partners ApS",
  "location": "Aalborg",
  "job_URL": "https://forestpartners.teamtailor.com/jobs/5631951-modebooker-group-online-a-s"
 },
 {
  "category": "salg",
  "pub_date": "05-03-2025",
  "title": "Handelstrainee med speciale i salg",
  "company": "Carl Ras A/S",
  "location": "Aalborg",
  "job_URL": "https://app.jobmatchprofile.com/6ye57d/carl-ras-as/75chpd/handelstrainee-med-speciale-i-salg"
 },
 {
  "category": "salg",
  "pub_date": "05-03-2025",
  "title": "Technical Sales Support Engineer",
  "company": "Scanico A/S",
  "location": "Aalborg",
  "job_URL": "https://www.jobindex.dk/jobannonce/h1534575/technical-sales-support-engineer"
 },
 {
  "category": "salg",
  "pub_date": "04-03-2025",
  "title": "Account Manager Retail",
  "company": "Cepelo A/S",
  "location": "Aalborg SV",
  "job_URL": "https://www.jobindex.dk/jobannonce/h1544723/account-manager-retail"
 },
 {
  "category": "salg",
  "pub_date": "04-03-2025",
  "title": "Master Data Specialist",
  "company": "Wrist Ship Supply",
  "location": "Nørresundby",
  "job_URL": "https://www.jobindex.dk/jobannonce/h1544687/master-data-specialist"
 },
 {
  "category": "kontor",
  "pub_date": "07-03-2025",
  "title": "Shippingkoordinator til international handelsvirksomhed",
  "company": "ESS-FOOD A/S",
  "location": "Aalborg, København V",
  "job_URL": "https://jobs.danishcrown.com/job/K%C3%B8benhavn-V-Shippingkoordinator-til-international-handelsvirksomhed-1620/1169413801/"
 },
 {
  "category": "kontor",
  "pub_date": "06-03-2025",
  "title": "Intern salgsmedarbejder til IBF i Nørresundby",
  "company": "A/S Ikast Betonvarefabrik (IBF)",
  "location": "Nørresundby",
  "job_URL": "https://ibf.career.emply.com/ad/intern-salgsmedarbejder-til-ibf-i-norresundby/ae93qx/da"
 },
 {
  "category": "kontor",
  "pub_date": "06-03-2025",
  "title": "Business Finance Consultant",
  "company": "Blue Power Partners A/S",
  "location": "Aalborg",
  "job_URL": "https://app.elvium.com/en/positions/29656/job_posting"
 },
 {
  "category": "kontor",
  "pub_date": "06-03-2025",
  "title": "Speditør til Skandinavien (Road)",
  "company": "Vendelbo Spedition A/S",
  "location": "Hjørring",
  "job_URL": "https://www.jobindex.dk/jobannonce/h1545364/speditoer-til-skandinavien-road"
 },
 {
  "category": "kontor",
  "pub_date": "06-03-2025",
  "title": "Front Office Assistant",
  "company": "NORDEX FOOD A/S",
  "location": "Nørager",
  "job_URL": "https://candidate.hr-manager.net/ApplicationInit.aspx?cid=2382&ProjectId=143685&DepartmentId=18961&MediaId=5"
 },
 {
  "category": "kontor",
  "pub_date": "06-03-2025",
  "title": "Afdelingschef for Support Erhverv Himmerland",
  "company": "Sparekassen Danmark",
  "location": "Aars eller Viborg",
  "job_URL": "https://www.jobindex.dk/jobannonce/h1545222/afdelingschef-for-support-erhverv-himmerland"
 },
 {
  "category": "kontor",
  "pub_date": "06-03-2025",
  "title": "Senior Group Financial Controller",
  "company": "Carsoe",
  "location": "Aalborg Øst",
  "job_URL": "https://candidate.hr-manager.net/ApplicationInit.aspx?cid=2042&ProjectId=143758&DepartmentId=18956&MediaId=4617"
 },
 {
  "category": "kontor",
  "pub_date": "06-03-2025",
  "title": "Få den bedste start på din karriere – bliv HANDELSELEV i kundeservice",
  "company": "Daarbak Redoffice",
  "location": "Aalborg SØ",
  "job_URL": "https://www.jobindex.dk/jobannonce/h1537645/faa-den-bedste-start-paa-din-karriere-bliv-handelselev-i-kundeservice"
 },
 {
  "category": "kontor",
  "pub_date": "06-03-2025",
  "title": "Få den bedste start på din karriere - bliv HANDELSELEV i kundeservice",
  "company": "Daarbak Design",
  "location": "Aalborg SØ",
  "job_URL": "https://www.jobindex.dk/jobannonce/h1537643/faa-den-bedste-start-paa-din-karriere-bliv-handelselev-i-kundeservice"
 },
 {
  "category": "kontor",
  "pub_date": "06-03-2025",
  "title": "Graduate program",
  "company": "Eurowind Energy A/S",
  "location": "Hobro",
  "job_URL": "https://eurowindenergy.com/uk/career?hr=show-job/233830&locale=en_US#hrskyen"
 },
 {
  "category": "kontor",
  "pub_date": "06-03-2025",
  "title": "Projektadministrator (økonom) ved Institut for Bæredygtighed og Planlægning",
  "company": "Aalborg Universitet",
  "location": "Aalborg og mulighed for hjemmearbejde",
  "job_URL": "https://www.stillinger.aau.dk/teknisk-administrative-stillinger/vis-stilling/vacancyId/1219480"
 },
 {
  "category": "kontor",
  "pub_date": "06-03-2025",
  "title": "Er du klar til at sikre effektiv logistik? Bliv logistikkoordinator hos Kongsberg!",
  "company": "Temp-Team A/S",
  "location": "Aalborg Øst",
  "job_URL": "https://temp-team.dk/job-search/er-du-klar-til-at-sikre-effektiv-logistik-bliv-logistikkoordinator-hos-kongsberg-420505"
 },
 {
  "category": "kontor",
  "pub_date": "06-03-2025",
  "title": "Værkfører Volvo Truck Center Aalborg",
  "company": "Volvo Truck Center Danmark A/S",
  "location": "Aalborg Øst",
  "job_URL": "https://www.jobindex.dk/jobannonce/h1545354/vaerkfoerer-volvo-truck-center-aalborg"
 },
 {
  "category": "kontor",
  "pub_date": "05-03-2025",
  "title": "Privatkunderådgiver til Erhverv Mariagerfjord i Hobro",
  "company": "Sparekassen Danmark",
  "location": "Hobro",
  "job_URL": "https://www.jobindex.dk/jobannonce/h1545073/privatkunderaadgiver-til-erhverv-mariagerfjord-i-hobro"
 },
 {
  "category": "kontor",
  "pub_date": "05-03-2025",
  "title": "Finance Manager til BILA Group",
  "company": "BILA A/S",
  "location": "Nykøbing M",
  "job_URL": "https://candidate.hr-manager.net/ApplicationInit.aspx?cid=1523&ProjectId=144278&DepartmentId=18957&MediaId=4614"
 },
 {
  "category": "kontor",
  "pub_date": "05-03-2025",
  "title": "Håndværkerbranchens ERP-system søger erfaren bogholder",
  "company": "E-Komplet ApS",
  "location": "Aalborg SV",
  "job_URL": "https://easyapply.jobs/r/jqKGbuj23KXClj3o0aRQ"
 },
 {
  "category": "kontor",
  "pub_date": "05-03-2025",
  "title": "Regnskabsassistent",
  "company": "A. Enggaard A/S, Entreprenør- og Byggefirma",
  "location": "Svenstrup J",
  "job_URL": "https://www.jobindex.dk/jobannonce/h1544903/regnskabsassistent"
 },
 {
  "category": "kontor",
  "pub_date": "05-03-2025",
  "title": "Speditør",
  "company": "Arctic Import A/S",
  "location": "Aalborg Øst",
  "job_URL": "https://www.jobindex.dk/jobannonce/h1544834/speditoer"
 },
 {
  "category": "oevrige",
  "pub_date": "07-03-2025",
  "title": "Studiemedhjælper til Finans - Power BI & Dataanalyse - Körber Supply Chain",
  "company": "Körber Supply Chain DK A/S",
  "location": "Svenstrup J",
  "job_URL": "https://jobs.koerber.com/job/Svenstrup-Studiemedhj%C3%A6lper-til-Finans-Power-BI-&-Dataanalyse-K%C3%B6rber-Supply-Chain/1169413201/"
 },
 {
  "category": "oevrige",
  "pub_date": "06-03-2025",
  "title": "Få den bedste start på din karriere – bliv HANDELSELEV i kundeservice",
  "company": "Daarbak Redoffice",
  "location": "Aalborg SØ",
  "job_URL": "https://www.jobindex.dk/jobannonce/h1537645/faa-den-bedste-start-paa-din-karriere-bliv-handelselev-i-kundeservice"
 },
 {
  "category": "oevrige",
  "pub_date": "06-03-2025",
  "title": "Få den bedste start på din karriere - bliv HANDELSELEV i kundeservice",
  "company": "Daarbak Design",
  "location": "Aalborg SØ",
  "job_URL": "https://www.jobindex.dk/jobannonce/h1537643/faa-den-bedste-start-paa-din-karriere-bliv-handelselev-i-kundeservice"
 },
 {
  "category": "oevrige",
  "pub_date": "05-03-2025",
  "title": "Handelstrainee med speciale i salg",
  "company": "Carl Ras A/S",
  "location": "Aalborg",
  "job_URL": "https://app.jobmatchprofile.com/6ye57d/carl-ras-as/75chpd/handelstrainee-med-speciale-i-salg"
 },
 {
  "category": "oevrige",
  "pub_date": "05-03-2025",
  "title": "Studentermedhjælper til analyseafdelingen",
  "company": "Nordiske Medier A/S",
  "location": "Aalborg",
  "job_URL": "https://detnordjyskemediehus.dk/job-og-karriere/ledige-stillinger/job-detail/?vid=20250305&locationId=3911"
 },
 {
  "category": "oevrige",
  "pub_date": "04-03-2025",
  "title": "Salgselev ILVA Frederikshavn - vi har fokus på DIN udvikling",
  "company": "ILVA",
  "location": "Frederikshavn",
  "job_URL": "https://ilva.youngcrm.com/jobportal/11021"
 },
 {
  "category": "oevrige",
  "pub_date": "04-03-2025",
  "title": "Sommerferieafløsere til hjemmeplejen i Team Sydthy",
  "company": "THISTED KOMMUNE",
  "location": "Hurup Thy",
  "job_URL": "https://portal.signatur.dk/ExtJobs/DefaultHosting/JobDetails.aspx?ClientId=1546&WebAdId=135852"
 },
 {
  "category": "oevrige",
  "pub_date": "03-03-2025",
  "title": "Praktik i Data eller Salg",
  "company": "BILA A/S",
  "location": "Nykøbing Mors",
  "job_URL": "https://candidate.hr-manager.net/ApplicationInit.aspx?cid=1523&ProjectId=144269&DepartmentId=18958&MediaId=4614"
 },
 {
  "category": "oevrige",
  "pub_date": "03-03-2025",
  "title": "Praktik i EL-konstruktion",
  "company": "BILA A/S",
  "location": "Nykøbing Mors",
  "job_URL": "https://candidate.hr-manager.net/ApplicationInit.aspx?cid=1523&ProjectId=144270&DepartmentId=18958&MediaId=4614"
 },
 {
  "category": "oevrige",
  "pub_date": "03-03-2025",
  "title": "Praktik i mekanisk konstruktion",
  "company": "BILA A/S",
  "location": "Nykøbing Mors eller Herning",
  "job_URL": "https://candidate.hr-manager.net/ApplicationInit.aspx?cid=1523&ProjectId=144271&DepartmentId=18958&MediaId=4614"
 },
 {
  "category": "oevrige",
  "pub_date": "03-03-2025",
  "title": "Praktik i projektledelse",
  "company": "BILA A/S",
  "location": "Nykøbing Mors, Herning eller Randers SV",
  "job_URL": "https://candidate.hr-manager.net/ApplicationInit.aspx?cid=1523&ProjectId=144272&DepartmentId=18958&MediaId=4614"
 },
 {
  "category": "oevrige",
  "pub_date": "03-03-2025",
  "title": "Praktik i Softwareprogrammering",
  "company": "BILA A/S",
  "location": "Nykøbing Mors",
  "job_URL": "https://candidate.hr-manager.net/ApplicationInit.aspx?cid=1523&ProjectId=144273&DepartmentId=18958&MediaId=4614"
 },
 {
  "category": "oevrige",
  "pub_date": "03-03-2025",
  "title": "Begynd din karriere med en elevplads hos Scan Global Logistics",
  "company": "Scan Global Logistics",
  "location": "Billund, Hvidovre, Viby J, Esbjerg Ø, Nørresundby",
  "job_URL": "https://scangl-v2-2-1.career.emply.com/ad/begynd-din-karriere-med-en-elevplads-hos-scan-global-logistics/u917l0/en"
 }
]