[
 {
  "link": "/Netto?publication=wIJdOc7a&offer=xhTVbgrXp5VBJlcTsxTVf",
  "price": "12",
  "currency": "DKK",
  "valid_from": "14-11-2025",
  "valid_until": "21-11-2025",
  "image": "https://image-transformer-api.tjek.com/?u=s3%3A%2F%2Fsgn-prd-assets%2Fuploads%2FwIJdOc7a%2Fp-2.webp&w=300&x1r=0.0126&x2r=0.4725&y1r=0.0123&y2r=0.3526&s=b92245725d7d6d6c75e8760e6147d662"
 },
 {
  "link": "/Lidl?publication=uxXaGXIx&offer=-Zo-IHJqFJwYSMcxopeq2",
  "price": "7",
  "currency": "DKK",
  "valid_from": "22-11-2025",
  "valid_until": "29-11-2025",
  "image": "https://image-transformer-api.tjek.com/?u=s3%3A%2F%2Fsgn-prd-assets%2Fuploads%2FlsGjPuXk%2Fp-1.webp&w=300&x1r=0.0028&x2r=0.338&y1r=0.4078&y2r=0.6608&s=295db934836dd55e591b2a5a4121a5b5"
 },
 {
  "link": "/fotex?publication=XYhhL8c1&offer=fKE_L1qXJ4_fmjywo-RRC",
  "price": "9",
  "currency": "DKK",
  "valid_from": "13-11-2025",
  "valid_until": "27-11-2025",
  "image": "https://image-transformer-api.tjek.com/?u=s3%3A%2F%2Fsgn-prd-assets%2Fuploads%2FXYhhL8c1%2Fp-48.webp&w=300&x1r=0.0035&x2r=0.585&y1r=0.6788&y2r=0.9998&s=482f33089425292289e199540acd9d71"
 },
 {
  "link": "/fotex?publication=XYhhL8c1&offer=DPz_Au3iipyhb1Ct84KR8",
  "price": "9",
  "currency": "DKK",
  "valid_from": "13-11-2025",
  "valid_until": "27-11-2025",
  "image": "https://image-transformer-api.tjek.com/?u=s3%3A%2F%2Fsgn-prd-assets%2Fuploads%2FXYhhL8c1%2Fp-39.webp&w=300&x1r=0.0146&x2r=0.3053&y1r=0.7117&y2r=0.98&s=68fda8c64378519ddef65e986e093699"
 },
 {
  "link": "/SPAR?publication=nNr3puAL&offer=q2Ef59YArnGeHCpNm-ClG",
  "price": "16",
  "currency": "DKK",
  "valid_from": "20-11-2025",
  "valid_until": "27-11-2025",
  "image": "https://image-transformer-api.tjek.com/?u=s3%3A%2F%2Fsgn-prd-assets%2Fuploads%2FnNr3puAL%2Fp-9.webp&w=300&x1r=0.4973&x2r=0.9699&y1r=0.6528&y2r=0.9545&s=1f3d7f3209d13fc79428b9c546a55e93"
 },
 {
  "link": "/Netto?publication=a90scz6e&offer=aBtX4WUhf7NKH4RVSKAS4",
  "price": "25",
  "currency": "DKK",
  "valid_from": "21-11-2025",
  "valid_until": "28-11-2025",
  "image": "https://image-transformer-api.tjek.com/?u=s3%3A%2F%2Fsgn-prd-assets%2Fuploads%2Fa90scz6e%2Fp-22.webp&w=300&x1r=0&x2r=1&y1r=0.0426&y2r=0.3539&s=9e273f8afad5eb7e7a57c325a2d34a88"
 },
 {
  "link": "/LET-KOB?publication=W0URqduT&offer=k0KceXzkRluIF-9dY7fjq",
  "price": "32",
  "currency": "DKK",
  "valid_from": "16-11-2025",
  "valid_until": "30-11-2025",
  "image": "https://image-transformer-api.tjek.com/?u=s3%3A%2F%2Fsgn-prd-assets%2Fuploads%2FW0URqduT%2Fp-7.webp&w=300&x1r=0.0265&x2r=0.5028&y1r=0.3562&y2r=0.6553&s=db7d5e35c91fe3970ccbba337f35b79a"
 },
 {
  "link": "/MENY?publication=137UTpn7&offer=FfCqaQO98RPPmRQu7ryoT",
  "price": "30",
  "currency": "DKK",
  "valid_from": "20-11-2025",
  "valid_until": "27-11-2025",
  "image": "https://image-transformer-api.tjek.com/?u=s3%3A%2F%2Fsgn-prd-assets%2Fuploads%2F137UTpn7%2Fp-19.webp&w=300&x1r=0.4969&x2r=0.9887&y1r=0.0138&y2r=0.4886&s=e1c0010cfc9927f233d74e3dd1eeebf2"
 },
 {
  "link": "/SPAR?publication=nNr3puAL&offer=7Qp9UFyMaTpsOeepSxBs4",
  "price": "99",
  "currency": "DKK",
  "valid_from": "20-11-2025",
  "valid_until": "27-11-2025",
  "image": "https://image-transformer-api.tjek.com/?u=s3%3A%2F%2Fsgn-prd-assets%2Fuploads%2FnNr3puAL%2Fp-1.webp&w=300&x1r=0.0202&x2r=0.985&y1r=0.1435&y2r=0.5159&s=9048eeb2d3c4f67dcdde0e455779e2ae"
 },
 {
  "link": "/fotex?publication=SA9Uh-ZU&offer=Qso8Kq29CCZXSDZr4BWVt",
  "price": "105",
  "currency": "DKK",
  "valid_from": "20-11-2025",
  "valid_until": "27-11-2025",
  "image": "https://image-transformer-api.tjek.com/?u=s3%3A%2F%2Fsgn-prd-assets%2Fuploads%2FSA9Uh-ZU%2Fp-25.webp&w=300&x1r=0.0035&x2r=0.5123&y1r=0.4843&y2r=0.9648&s=84136f1cd26cfe55dc293b22dcfcebf4"
 },
 {
  "link": "/MENY?publication=137UTpn7&offer=jk_WPdpyxWSABBeHGeT-Q",
  "price": "112",
  "currency": "DKK",
  "valid_from": "20-11-2025",
  "valid_until": "27-11-2025",
  "image": "https://image-transformer-api.tjek.com/?u=s3%3A%2F%2Fsgn-prd-assets%2Fuploads%2F137UTpn7%2Fp-32.webp&w=300&x1r=0.6109&x2r=0.9926&y1r=0.6937&y2r=0.985&s=4052dfa7400e6d5ed23e83e649df3649"
 },
 {
  "link": "/Min-Kobmand?publication=0fB7-UZb&offer=0qfXQc-znBMe8p0ROt0E5",
  "price": "99",
  "currency": "DKK",
  "valid_from": "20-11-2025",
  "valid_until": "27-11-2025",
  "image": "https://image-transformer-api.tjek.com/?u=s3%3A%2F%2Fsgn-prd-assets%2Fuploads%2F0fB7-UZb%2Fp-1.webp&w=300&x1r=0.4891&x2r=0.9795&y1r=0.618&y2r=0.8734&s=e817562e4c1601c50fa612a087504eb3"
 },
 {
  "link": "/LET-KOB?publication=W0URqduT&offer=mvf_u2DJoZpPjk7s7Xapn",
  "price": "110",
  "currency": "DKK",
  "valid_from": "16-11-2025",
  "valid_until": "30-11-2025",
  "image": "https://image-transformer-api.tjek.com/?u=s3%3A%2F%2Fsgn-prd-assets%2Fuploads%2FW0URqduT%2Fp-1.webp&w=300&x1r=0.0146&x2r=0.9915&y1r=0.5863&y2r=0.9233&s=b3d6cb3578cdccedbd5b0e80decfb662"
 },
 {
  "link": "/fotex?publication=XYhhL8c1&offer=E-emo5ZtWBObiuZlxRWAQ",
  "price": "112",
  "currency": "DKK",
  "valid_from": "13-11-2025",
  "valid_until": "27-11-2025",
  "image": "https://image-transformer-api.tjek.com/?u=s3%3A%2F%2Fsgn-prd-assets%2Fuploads%2FXYhhL8c1%2Fp-10.webp&w=300&x1r=0&x2r=1&y1r=0.6211&y2r=0.9758&s=20d0017f1d3a4b6b29c4ea139494cd93"
 },
 {
  "link": "/MENY?publication=137UTpn7&offer=Wic7dnuWOu7EaTjn1-vC9",
  "price": "35",
  "currency": "DKK",
  "valid_from": "20-11-2025",
  "valid_until": "27-11-2025",
  "image": "https://image-transformer-api.tjek.com/?u=s3%3A%2F%2Fsgn-prd-assets%2Fuploads%2F137UTpn7%2Fp-30.webp&w=300&x1r=0.0111&x2r=0.9858&y1r=0.1827&y2r=0.6585&s=fc9d2457f4f91c71fd89fa53a328f6d7"
 },
 {
  "link": "/REMA-1000?publication=JVCZOqH9&offer=TdDPwkGVB3gaLGoxHC8ig",
  "price": "5",
  "currency": "DKK",
  "valid_from": "22-11-2025",
  "valid_until": "29-11-2025",
  "image": "https://image-transformer-api.tjek.com/?u=s3%3A%2F%2Fsgn-prd-assets%2Fuploads%2FJVCZOqH9%2Fp-10.webp&w=300&x1r=0.5409&x2r=0.9974&y1r=0.0809&y2r=0.4097&s=992a924cf0989d247b6d141ce6a0b31d"
 },
 {
  "link": "/fotex?publication=XYhhL8c1&offer=sZg-gwIdzxfuIXZ4l-2x7",
  "price": "135",
  "currency": "DKK",
  "valid_from": "13-11-2025",
  "valid_until": "27-11-2025",
  "image": "https://image-transformer-api.tjek.com/?u=s3%3A%2F%2Fsgn-prd-assets%2Fuploads%2FXYhhL8c1%2Fp-37.webp&w=300&x1r=0.2506&x2r=0.7169&y1r=0.7299&y2r=0.9531&s=c609d89647073b7a24e52ff3bd901690"
 },
 {
  "link": "/Bilka?publication=_XdUwPWv&offer=-W2H25I6fK6DCiW8h5ZIu",
  "price": "109",
  "currency": "DKK",
  "valid_from": "20-11-2025",
  "valid_until": "27-11-2025",
  "image": "https://image-transformer-api.tjek.com/?u=s3%3A%2F%2Fsgn-prd-assets%2Fuploads%2F_XdUwPWv%2Fp-27.webp&w=300&x1r=0.5042&x2r=0.9809&y1r=0.4534&y2r=0.9436&s=34cd0e55a7a2fa916902ddb085b7b6bf"
 },
 {
  "link": "/Min-Kobmand?publication=0fB7-UZb&offer=b-bQETrv73tTclWxXBVbl",
  "price": "69",
  "currency": "DKK",
  "valid_from": "20-11-2025",
  "valid_until": "27-11-2025",
  "image": "https://image-transformer-api.tjek.com/?u=s3%3A%2F%2Fsgn-prd-assets%2Fuploads%2F0fB7-UZb%2Fp-15.webp&w=300&x1r=0.0307&x2r=0.4966&y1r=0.6513&y2r=0.9786&s=823f77cc7e149be0877a36651fd1b519"
 },
 {
  "link": "/MENY?publication=137UTpn7&offer=5AhxNHdi5P1SKzfYuaiov",
  "price": "135",
  "currency": "DKK",
  "valid_from": "20-11-2025",
  "valid_until": "27-11-2025",
  "image": "https://image-transformer-api.tjek.com/?u=s3%3A%2F%2Fsgn-prd-assets%2Fuploads%2F137UTpn7%2Fp-32.webp&w=300&x1r=0.6132&x2r=0.9827&y1r=0.3383&y2r=0.6971&s=c61face382302f5e7f90314d8bd57f47"
 },
 {
  "link": "/SPAR?publication=nNr3puAL&offer=QcF7KEF8Nv7mJ7tRAGY0C",
  "price": "112",
  "currency": "DKK",
  "valid_from": "20-11-2025",
  "valid_until": "27-11-2025",
  "image": "https://image-transformer-api.tjek.com/?u=s3%3A%2F%2Fsgn-prd-assets%2Fuploads%2FnNr3puAL%2Fp-20.webp&w=300&x1r=0.5293&x2r=0.9696&y1r=0.2778&y2r=0.5455&s=5639af00041f4ea286503177e7bcaff5"
 },
 {
  "link": "/BorderShop?publication=AuF9FQjK&offer=EA8yN2W1bptmM0DoMPKVf",
  "price": "75",
  "currency": "DKK",
  "valid_from": "04-11-2025",
  "valid_until": "30-12-2025",
  "image": "https://image-transformer-api.tjek.com/?u=s3%3A%2F%2Fsgn-prd-assets%2Fuploads%2FAuF9FQjK%2Fp-13.webp&w=300&x1r=0.2891&x2r=0.6913&y1r=0.5833&y2r=0.875&s=80cc044b2892c0c5aaedfc88f4bcf2ee"
 },
 {
  "link": "/Wolt-Market?publication=ZD4TZWig&offer=7k7KhFFlWMeuSKk-96MHR",
  "price": "46",
  "currency": "DKK",
  "valid_from": "17-11-2025",
  "valid_until": "24-11-2025",
  "image": "https://image-transformer-api.tjek.com/?u=s3%3A%2F%2Fsgn-prd-assets%2Fuploads%2Fbusiness_images%2Fi7NdvM%2Fe0ebb8fb1956237806e62a2a178fbe1b%2Cs3%3A%2F%2Fsgn-prd-assets%2Fuploads%2Fbusiness_images%2Fi7NdvM%2F001a26e43cf358712658531ff0e16dea%2Cs3%3A%2F%2Fsgn-prd-assets%2Fuploads%2Fbusiness_images%2Fi7NdvM%2F16e311c0f195535fa7cd34673db9d8a4%2Cs3%3A%2F%2Fsgn-prd-assets%2Fuploads%2Fbusiness_images%2Fi7NdvM%2F5ca9e1af9443fc29941d70e7d4da82cd&w=300&s=000b0b8b2d0e50b2a672be9cd237df0c"
 },
 {
  "link": "/Fleggaard?publication=wv9g2OWv&offer=534qSQW4_IY9mwQgq-jnu",
  "price": "75",
  "currency": "DKK",
  "valid_from": "04-11-2025",
  "valid_until": "25-11-2025",
  "image": "https://image-transformer-api.tjek.com/?u=s3%3A%2F%2Fsgn-prd-bumblebee%2Ffeed-images%2Fc61b3e4240a41fc49ba9eaa9c8753899&w=300&s=82a77e0ef10e0129d8c8ee44d8214a89"
 },
 {
  "link": "/Calle?publication=wBzX_0dJ&offer=YaBSRCDLazLABL1QG68lp",
  "price": "75",
  "currency": "DKK",
  "valid_from": "04-11-2025",
  "valid_until": "25-11-2025",
  "image": "https://image-transformer-api.tjek.com/?u=s3%3A%2F%2Fsgn-prd-bumblebee%2Ffeed-images%2F43110999e6485119ef547f2dde21a1ff&w=300&s=4808e3accb95bd83dd8c2bfd131c8f82"
 },
 {
  "link": "/CITTI?publication=9ha8BHjb&offer=5xBUPIWgR9lYRkMcRqBix",
  "price": "79.99",
  "currency": "DKK",
  "valid_from": "28-10-2025",
  "valid_until": "25-11-2025",
  "image": "https://image-transformer-api.tjek.com/?u=s3%3A%2F%2Fsgn-prd-assets%2Fuploads%2F9ha8BHjb%2Fp-17.webp&w=300&x1r=0.5137&x2r=0.9991&y1r=0.5352&y2r=0.8079&s=d118574954c5635a49e10b47b8429443"
 },
 {
  "link": "/Kobmandsgarden?publication=VngZhrfx&offer=RKjqMGVJovbciIhSOn1pT",
  "price": "79",
  "currency": "DKK",
  "valid_from": "28-10-2025",
  "valid_until": "25-11-2025",
  "image": "https://image-transformer-api.tjek.com/?u=s3%3A%2F%2Fsgn-prd-assets%2Fuploads%2FVngZhrfx%2Fp-19.webp&w=300&x1r=0&x2r=1&y1r=0.0642&y2r=0.9913&s=f0284493e3facea89f8cba21ac5b45cc"
 },
 {
  "link": "/Otto-Duborg?publication=FmukgUKg&offer=DjrmoaUiFfu9J_KIH5GAF",
  "price": "79.99",
  "currency": "DKK",
  "valid_from": "29-10-2025",
  "valid_until": "26-11-2025",
  "image": "https://image-transformer-api.tjek.com/?u=s3%3A%2F%2Fsgn-prd-assets%2Fuploads%2FFmukgUKg%2Fp-19.webp&w=300&x1r=0.6033&x2r=0.9549&y1r=0.0859&y2r=0.3584&s=7c37d252734bdde5dad5ef341225bb6a"
 },
 {
  "link": "/Nielsen-Scan-Shop?publication=5l23V3Tt&offer=QzIeg-aasU8dQNW-KdbuI",
  "price": "75",
  "currency": "DKK",
  "valid_from": "29-10-2025",
  "valid_until": "26-11-2025",
  "image": "https://image-transformer-api.tjek.com/?u=s3%3A%2F%2Fsgn-prd-assets%2Fuploads%2F5l23V3Tt%2Fp-1.webp&w=300&x1r=0.5836&x2r=0.9736&y1r=0.3643&y2r=0.619&s=7d3fe64f94d0090c106e333fd1340113"
 },
 {
  "link": "/Scandlines-Travel-Shop?publication=of9didoH&offer=uIPhKz7K1vfZdnB9YVJDN",
  "price": "89.95",
  "currency": "DKK",
  "valid_from": "21-09-2025",
  "valid_until": "31-12-2025",
  "image": "https://image-transformer-api.tjek.com/?u=s3%3A%2F%2Fsgn-prd-assets%2Fuploads%2Fof9didoH%2Fp-61.webp&w=300&x1r=0.0154&x2r=0.4892&y1r=0.034&y2r=0.477&s=342ed7bae7810d04b5d3adecb18a7ea4"
 },
 {
  "link": "/Scandinavian-Park?publication=ZRG2wnAa&offer=irtOtAdT8QYsQIwQYnpXx",
  "price": "74.99",
  "currency": "DKK",
  "valid_from": "29-10-2025",
  "valid_until": "26-11-2025",
  "image": "https://image-transformer-api.tjek.com/?u=s3%3A%2F%2Fsgn-prd-assets%2Fuploads%2FZRG2wnAa%2Fp-2.webp&w=300&x1r=0.0056&x2r=0.6499&y1r=0.0158&y2r=0.5043&s=5efe3d5a75a583130c6024da743f813f"
 },
 {
  "link": "/Poetzsch-Padborg?publication=eeSQDD3N&offer=9dyGWC9t3JvAx-vWfgxOF",
  "price": "79.99",
  "currency": "DKK",
  "valid_from": "29-10-2025",
  "valid_until": "26-11-2025",
  "image": "https://image-transformer-api.tjek.com/?u=s3%3A%2F%2Fsgn-prd-assets%2Fuploads%2FeeSQDD3N%2Fp-24.webp&w=300&x1r=0.0192&x2r=0.342&y1r=0.0695&y2r=0.3711&s=97cdeff807dee04b7ba424b125e61e75"
 },
 {
  "link": "/fotex?publication=XYhhL8c1&offer=XZe48cNi6k5_as35XNCd-",
  "price": "112",
  "currency": "DKK",
  "valid_from": "13-11-2025",
  "valid_until": "27-11-2025",
  "image": "https://image-transformer-api.tjek.com/?u=s3%3A%2F%2Fsgn-prd-assets%2Fuploads%2FXYhhL8c1%2Fp-37.webp&w=300&x1r=0.666&x2r=0.9969&y1r=0.669&y2r=0.9583&s=b9d0d4a4ab00ce1b9b460629267e1196"
 }
]