[
 {
  "link": "/SPAR/tilbud/Yoggi-Yoghurt~o:felTQL0c7hMn5yiG77p66",
  "price": "12.00",
  "currency": "DKK",
  "valid_from": "06-02-2025",
  "valid_until": "13-02-2025",
  "image": "https://image-transformer-api.tjek.com/?u=s3%3A%2F%2Fsgn-prd-assets%2Fuploads%2Fc0_iiunz%2Fp-1.webp&w=100&x1r=0.4863&x2r=0.9841&y1r=0.1475&y2r=0.6576&s=4b1002526c5468c1f52567d8ec31c06f"
 },
 {
  "link": "/Min-Kobmand/tilbud/Yoggi-Yoghurt~o:euMAgX4G8ev2uzPV-iO0T",
  "price": "12.00",
  "currency": "DKK",
  "valid_from": "30-01-2025",
  "valid_until": "06-02-2025",
  "image": "https://image-transformer-api.tjek.com/?u=s3%3A%2F%2Fsgn-prd-assets%2Fuploads%2Fh_m6cTEs%2Fp-1.webp&w=100&x1r=0.0263&x2r=0.5022&y1r=0.2403&y2r=0.5696&s=3c136375d8c95ae222784ecd841e1ccf"
 },
 {
  "link": "/Bilka/tilbud/Yoggi-yoghurt~o:iWw4Y8vfUY85Rq5WpoWP2",
  "price": "22.00",
  "currency": "DKK",
  "valid_from": "06-02-2025",
  "valid_until": "13-02-2025",
  "image": "https://image-transformer-api.tjek.com/?u=s3%3A%2F%2Fsgn-prd-assets%2Fuploads%2F6SigckzE%2Fp-1.webp&w=100&x1r=0.4671&x2r=0.7037&y1r=0.5319&y2r=0.7982&s=eeaebb2a356738c9e8914efba555ef8f"
 },
 {
  "link": "/Kvickly/tilbud/Quaker-Crueesli-morgenmad~o:ar7p4P7SCOGn3It-Wf-9x",
  "price": "109.00",
  "currency": "DKK",
  "valid_from": "30-01-2025",
  "valid_until": "06-02-2025",
  "image": "https://image-transformer-api.tjek.com/?u=s3%3A%2F%2Fsgn-prd-assets%2Fuploads%2FykouMbPf%2Fp-45.webp&w=100&x1r=0&x2r=0.6801&y1r=0.0065&y2r=0.4574&s=3881dc06a8aabccddb9a554f198be965"
 },
 {
  "link": "/SuperBrugsen/tilbud/Quaker-Crueesli-morgenmad~o:NodazFSw4OO7wHGKJavDZ",
  "price": "109.00",
  "currency": "DKK",
  "valid_from": "30-01-2025",
  "valid_until": "06-02-2025",
  "image": "https://image-transformer-api.tjek.com/?u=s3%3A%2F%2Fsgn-prd-assets%2Fuploads%2FmEk5AErd%2Fp-43.webp&w=100&x1r=0&x2r=0.6794&y1r=0.0065&y2r=0.4572&s=05d3526160b7ae6c26d137635f1133ac"
 },
 {
  "link": "/REMA-1000/tilbud/Tuborg-Classic-Gron-Tuborg-Gron-Tuborg-0.0-eller-Tuborg-sprod-33-cl.-Ex.-pant~o:kI5M01gOLkiYowakB0Xlx",
  "price": "4.50",
  "currency": "DKK",
  "valid_from": "08-02-2025",
  "valid_until": "15-02-2025",
  "image": "https://image-transformer-api.tjek.com/?u=s3%3A%2F%2Fsgn-prd-assets%2Fuploads%2FOlO7mGAJ%2Fp-20.webp&w=100&x1r=0.0062&x2r=0.5068&y1r=0.2843&y2r=0.6631&s=5dc95a13a3146aa9ecc3d1db1e12d6fe"
 },
 {
  "link": "/fotex/tilbud/Carlsberg-Gron-Tuborg-eller-Tuborg-Classic-flasker~o:XpZqlKfHZhFpXOXOdhqnm",
  "price": "135.00",
  "currency": "DKK",
  "valid_from": "30-01-2025",
  "valid_until": "13-02-2025",
  "image": "https://image-transformer-api.tjek.com/?u=s3%3A%2F%2Fsgn-prd-assets%2Fuploads%2FePzHcQ5K%2Fp-43.webp&w=100&x1r=0.4735&x2r=0.9835&y1r=0.3127&y2r=0.7172&s=a2439878adc1a27fd604a98c0b5d634a"
 },
 {
  "link": "/MENY/tilbud/GRON-TUBORG-ELLER-TUBORG-CLASSIC-ALKOHOLFRI~o:lcpENtoBcdX2QoCE00h4Z",
  "price": "35.00",
  "currency": "DKK",
  "valid_from": "06-02-2025",
  "valid_until": "13-02-2025",
  "image": "https://image-transformer-api.tjek.com/?u=s3%3A%2F%2Fsgn-prd-assets%2Fuploads%2FhOQE1_Jz%2Fp-32.webp&w=100&x1r=0.261&x2r=0.5751&y1r=0.3611&y2r=0.6384&s=fcd22440d051498b04d12f9014844308"
 },
 {
  "link": "/MENY/tilbud/GRON-TUBORG-TUBORG-CLASSIC-ELLER-TUBORG-SPROD~o:eYY-KKZlOMAq2XrBb4uhc",
  "price": "72.00",
  "currency": "DKK",
  "valid_from": "31-01-2025",
  "valid_until": "28-02-2025",
  "image": "https://image-transformer-api.tjek.com/?u=s3%3A%2F%2Fsgn-prd-assets%2Fuploads%2FhOQE1_Jz%2Fp-34.webp&w=100&x1r=0.5077&x2r=0.9962&y1r=0.6657&y2r=0.9581&s=c74bf3d758a86c66136809ef80d39d7b"
 },
 {
  "link": "/MENY/tilbud/GRON-TUBORG-TUBORG-CLASSIC-ELLER-CARLSBERG-PILSNER~o:VGQjb-KPNUFoxPOz1WrzB",
  "price": "115.00",
  "currency": "DKK",
  "valid_from": "06-02-2025",
  "valid_until": "13-02-2025",
  "image": "https://image-transformer-api.tjek.com/?u=s3%3A%2F%2Fsgn-prd-assets%2Fuploads%2FhOQE1_Jz%2Fp-39.webp&w=100&x1r=0.5052&x2r=0.9799&y1r=0.6163&y2r=0.914&s=e06d3112dd757c532e706106c05af3bc"
 },
 {
  "link": "/Netto/tilbud/Gron-Tuborg-Tuborg-Classic-eller-Classic-alkoholfri~o:9J-ZiIAd7ynqU_a3C1mHw",
  "price": "79.00",
  "currency": "DKK",
  "valid_from": "31-01-2025",
  "valid_until": "07-02-2025",
  "image": "https://image-transformer-api.tjek.com/?u=s3%3A%2F%2Fsgn-prd-assets%2Fuploads%2FawqcX_-Y%2Fp-19.webp&w=100&x1r=0.6528&x2r=0.9933&y1r=0.6889&y2r=0.9752&s=b9b10d27f1c6c02436451b57c778c419"
 },
 {
  "link": "/SPAR/tilbud/Gron-Tuborg-Tuborg-Classic-eller-Tuborg-Sprod~o:haoHKOehb-PVD5xbQoAYi",
  "price": "72.00",
  "currency": "DKK",
  "valid_from": "31-01-2025",
  "valid_until": "28-02-2025",
  "image": "https://image-transformer-api.tjek.com/?u=s3%3A%2F%2Fsgn-prd-assets%2Fuploads%2Fc0_iiunz%2Fp-21.webp&w=100&x1r=0.6454&x2r=0.9719&y1r=0.2808&y2r=0.4999&s=ae8934532f4d44e7281fb3737a2b8a04"
 },
 {
  "link": "/SPAR/tilbud/Gron-Tuborg-Tuborg-Classic-eller-Carlsberg-Pilsner~o:G9LV5HzKp6dPHSgvqC12U",
  "price": "135.00",
  "currency": "DKK",
  "valid_from": "06-02-2025",
  "valid_until": "13-02-2025",
  "image": "https://image-transformer-api.tjek.com/?u=s3%3A%2F%2Fsgn-prd-assets%2Fuploads%2Fc0_iiunz%2Fp-21.webp&w=100&x1r=0.0327&x2r=0.9676&y1r=0.6915&y2r=0.9645&s=dc6b19a71a04dc99800bf4acfe073140"
 },
 {
  "link": "/Min-Kobmand/tilbud/Gron-Tuborg-Tuborg-Classic-eller-Tuborg-Sprod~o:ge712jD5HL1B-ppPvwBxa",
  "price": "72.00",
  "currency": "DKK",
  "valid_from": "31-01-2025",
  "valid_until": "28-02-2025",
  "image": "https://image-transformer-api.tjek.com/?u=s3%3A%2F%2Fsgn-prd-assets%2Fuploads%2Fh_m6cTEs%2Fp-2.webp&w=100&x1r=0.5053&x2r=0.9809&y1r=0.7025&y2r=0.9769&s=7a0bb15560b0a2c853e46a1b72b32b38"
 },
 {
  "link": "/Min-Kobmand/tilbud/Gron-Tuborg-Tuborg-Classic-eller-Carlsberg-Pilsner~o:-XnWFhcMdPmevWogTnFlY",
  "price": "135.00",
  "currency": "DKK",
  "valid_from": "06-02-2025",
  "valid_until": "13-02-2025",
  "image": "https://image-transformer-api.tjek.com/?u=s3%3A%2F%2Fsgn-prd-assets%2Fuploads%2FKortJ4nz%2Fp-15.webp&w=100&x1r=0.6527&x2r=0.9746&y1r=0.3798&y2r=0.7483&s=a519cdc557afc14f4b7e3c4a86816238"
 }
]