[
 {
  "match": "Frankrig – Spanien",
  "category": "FIBA Women's EuroBasket\n\t\t\t\t\t\t\t\t\t\t\t\tVBet Live odds",
  "time": "16:30",
  "date": "2025-06-27",
  "channels": [
   {
    "name": "DAZN",
    "logo_url": "https://www.tvsporten.dk/media/tvchannels/dazn-new-100x60-1.png"
   },
   {
    "name": "Norlys",
    "logo_url": "https://www.tvsporten.dk/media/tvchannels/norlys_100x60.jpg"
   }
  ]
 },
 {
  "match": "Østrigs Grand Prix",
  "category": "Formel 1\n\t\t\t\t\t\t\t\t\t\t\t\tVBet Live odds",
  "time": "17:00",
  "date": "2025-06-27",
  "channels": [
   {
    "name": "TV3 Sport",
    "logo_url": "https://www.tvsporten.dk/media/tvchannels/tv3_sport_2web.png"
   },
   {
    "name": "Viaplay.dk",
    "logo_url": "https://www.tvsporten.dk/media/tvchannels/viaplay_dk_web.png"
   },
   {
    "name": "V Sport Live 3",
    "logo_url": "https://www.tvsporten.dk/media/tvchannels/v-sport-live-3100x60-1.jpg"
   },
   {
    "name": "Norlys",
    "logo_url": "https://www.tvsporten.dk/media/tvchannels/norlys_100x60.jpg"
   }
  ]
 },
 {
  "match": "Valladolid P2",
  "category": "Premier Padel Tour\n\t\t\t\t\t\t\t\t\t\t\t\tVBet Live odds",
  "time": "17:00",
  "date": "2025-06-27",
  "channels": [
   {
    "name": "Viaplay.dk",
    "logo_url": "https://www.tvsporten.dk/media/tvchannels/viaplay_dk_web.png"
   },
   {
    "name": "Norlys",
    "logo_url": "https://www.tvsporten.dk/media/tvchannels/norlys_100x60.jpg"
   }
  ]
 },
 {
  "match": "Dow Championship",
  "category": "LPGA\n\t\t\t\t\t\t\t\t\t\t\t\tVBet Live odds",
  "time": "17:00",
  "date": "2025-06-27",
  "channels": [
   {
    "name": "Viaplay.dk",
    "logo_url": "https://www.tvsporten.dk/media/tvchannels/viaplay_dk_web.png"
   },
   {
    "name": "Norlys",
    "logo_url": "https://www.tvsporten.dk/media/tvchannels/norlys_100x60.jpg"
   }
  ]
 },
 {
  "match": "Alex Michelsen - Corentin Moutet",
  "category": "ATP\n\t\t\t\t\t\t\t\t\t\t\t\tVBet Live odds",
  "time": "18:00",
  "date": "2025-06-27",
  "channels": [
   {
    "name": "TV2 Play",
    "logo_url": "https://www.tvsporten.dk/media/tvchannels/tv2-play_100x60.jpg"
   },
   {
    "name": "Norlys",
    "logo_url": "https://www.tvsporten.dk/media/tvchannels/norlys_100x60.jpg"
   }
  ]
 },
 {
  "match": "Taylor Fritz - Alejandro Davidovich Fokina",
  "category": "ATP\n\t\t\t\t\t\t\t\t\t\t\t\tVBet Live odds",
  "time": "18:00",
  "date": "2025-06-27",
  "channels": [
   {
    "name": "TV2 Play",
    "logo_url": "https://www.tvsporten.dk/media/tvchannels/tv2-play_100x60.jpg"
   },
   {
    "name": "Norlys",
    "logo_url": "https://www.tvsporten.dk/media/tvchannels/norlys_100x60.jpg"
   }
  ]
 },
 {
  "match": "Rothesay International Eastbourne",
  "category": "ATP\n\t\t\t\t\t\t\t\t\t\t\t\tVBet Live odds",
  "time": "18:00",
  "date": "2025-06-27",
  "channels": [
   {
    "name": "TV2 Sport",
    "logo_url": "https://www.tvsporten.dk/media/tvchannels/tv2-sport_100x60.jpg"
   },
   {
    "name": "TV2 Play",
    "logo_url": "https://www.tvsporten.dk/media/tvchannels/tv2-play_100x60.jpg"
   },
   {
    "name": "Norlys",
    "logo_url": "https://www.tvsporten.dk/media/tvchannels/norlys_100x60.jpg"
   }
  ]
 },
 {
  "match": "LIV Golf Dallas",
  "category": "LIV Golf\n\t\t\t\t\t\t\t\t\t\t\t\tVBet Live odds",
  "time": "18:00",
  "date": "2025-06-27",
  "channels": [
   {
    "name": "DAZN",
    "logo_url": "https://www.tvsporten.dk/media/tvchannels/dazn-new-100x60-1.png"
   },
   {
    "name": "Norlys",
    "logo_url": "https://www.tvsporten.dk/media/tvchannels/norlys_100x60.jpg"
   }
  ]
 },
 {
  "match": "Rothesay International Eastbourne",
  "category": "ATP\n\t\t\t\t\t\t\t\t\t\t\t\tVBet Live odds",
  "time": "18:00",
  "date": "2025-06-27",
  "channels": [
   {
    "name": "TV2 Sport",
    "logo_url": "https://www.tvsporten.dk/media/tvchannels/tv2-sport_100x60.jpg"
   },
   {
    "name": "TV2 Play",
    "logo_url": "https://www.tvsporten.dk/media/tvchannels/tv2-play_100x60.jpg"
   },
   {
    "name": "Norlys",
    "logo_url": "https://www.tvsporten.dk/media/tvchannels/norlys_100x60.jpg"
   }
  ]
 },
 {
  "match": "Thorbjørn Olesen i Rocket Classic",
  "category": "PGA\n\t\t\t\t\t\t\t\t\t\t\t\tVBet Live odds",
  "time": "18:15",
  "date": "2025-06-27",
  "channels": [
   {
    "name": "Max",
    "logo_url": "https://www.tvsporten.dk/media/tvchannels/max-mobile.png"
   },
   {
    "name": "Norlys",
    "logo_url": "https://www.tvsporten.dk/media/tvchannels/norlys_100x60.jpg"
   }
  ]
 },
 {
  "match": "Dow Championship",
  "category": "LPGA\n\t\t\t\t\t\t\t\t\t\t\t\tVBet Live odds",
  "time": "18:30",
  "date": "2025-06-27",
  "channels": [
   {
    "name": "V Sport Golf",
    "logo_url": "https://www.tvsporten.dk/media/tvchannels/viasatgolf_web.png"
   },
   {
    "name": "Viaplay.dk",
    "logo_url": "https://www.tvsporten.dk/media/tvchannels/viaplay_dk_web.png"
   },
   {
    "name": "Norlys",
    "logo_url": "https://www.tvsporten.dk/media/tvchannels/norlys_100x60.jpg"
   }
  ]
 },
 {
  "match": "WRC Acropolis Race Greece",
  "category": "Rally\n\t\t\t\t\t\t\t\t\t\t\t\tVBet Live odds",
  "time": "18:30",
  "date": "2025-06-27",
  "channels": [
   {
    "name": "DAZN",
    "logo_url": "https://www.tvsporten.dk/media/tvchannels/dazn-new-100x60-1.png"
   },
   {
    "name": "Norlys",
    "logo_url": "https://www.tvsporten.dk/media/tvchannels/norlys_100x60.jpg"
   }
  ]
 },
 {
  "match": "U.S. Senior Open",
  "category": "PGA TOUR Champions\n\t\t\t\t\t\t\t\t\t\t\t\tVBet Live odds",
  "time": "19:30",
  "date": "2025-06-27",
  "channels": [
   {
    "name": "Viaplay.dk",
    "logo_url": "https://www.tvsporten.dk/media/tvchannels/viaplay_dk_web.png"
   },
   {
    "name": "Norlys",
    "logo_url": "https://www.tvsporten.dk/media/tvchannels/norlys_100x60.jpg"
   }
  ]
 },
 {
  "match": "Italien - Belgien",
  "category": "FIBA Women's EuroBasket\n\t\t\t\t\t\t\t\t\t\t\t\tVBet Live odds",
  "time": "19:30",
  "date": "2025-06-27",
  "channels": [
   {
    "name": "DAZN",
    "logo_url": "https://www.tvsporten.dk/media/tvchannels/dazn-new-100x60-1.png"
   },
   {
    "name": "Norlys",
    "logo_url": "https://www.tvsporten.dk/media/tvchannels/norlys_100x60.jpg"
   }
  ]
 },
 {
  "match": "Rasmus Højgaard i Rocket Classic",
  "category": "PGA\n\t\t\t\t\t\t\t\t\t\t\t\tVBet Live odds",
  "time": "19:45",
  "date": "2025-06-27",
  "channels": [
   {
    "name": "Max",
    "logo_url": "https://www.tvsporten.dk/media/tvchannels/max-mobile.png"
   },
   {
    "name": "Norlys",
    "logo_url": "https://www.tvsporten.dk/media/tvchannels/norlys_100x60.jpg"
   }
  ]
 },
 {
  "match": "U.S. Senior Open",
  "category": "PGA TOUR Champions\n\t\t\t\t\t\t\t\t\t\t\t\tVBet Live odds",
  "time": "20:00",
  "date": "2025-06-27",
  "channels": [
   {
    "name": "V Sport Golf",
    "logo_url": "https://www.tvsporten.dk/media/tvchannels/viasatgolf_web.png"
   },
   {
    "name": "Viaplay.dk",
    "logo_url": "https://www.tvsporten.dk/media/tvchannels/viaplay_dk_web.png"
   },
   {
    "name": "Norlys",
    "logo_url": "https://www.tvsporten.dk/media/tvchannels/norlys_100x60.jpg"
   }
  ]
 },
 {
  "match": "Rocket Mortgage Classic",
  "category": "PGA\n\t\t\t\t\t\t\t\t\t\t\t\tVBet Live odds",
  "time": "21:00",
  "date": "2025-06-27",
  "channels": [
   {
    "name": "Eurosport 2",
    "logo_url": "https://www.tvsporten.dk/media/tvchannels/eurosport2_web.png"
   },
   {
    "name": "Max",
    "logo_url": "https://www.tvsporten.dk/media/tvchannels/max-mobile.png"
   },
   {
    "name": "Norlys",
    "logo_url": "https://www.tvsporten.dk/media/tvchannels/norlys_100x60.jpg"
   }
  ]
 },
 {
  "match": "Danmark U21 - Sverige U21",
  "category": "VM U21\n\t\t\t\t\t\t\t\t\t\t\t\tVBet Live odds",
  "time": "21:00",
  "date": "2025-06-27",
  "channels": [
   {
    "name": "Viaplay.dk",
    "logo_url": "https://www.tvsporten.dk/media/tvchannels/viaplay_dk_web.png"
   },
   {
    "name": "Norlys",
    "logo_url": "https://www.tvsporten.dk/media/tvchannels/norlys_100x60.jpg"
   }
  ]
 },
 {
  "match": "Frankrig – Brasilien",
  "category": "Venskabskamp kvinder\n\t\t\t\t\t\t\t\t\t\t\t\tVBet Live odds",
  "time": "21:15",
  "date": "2025-06-27",
  "channels": [
   {
    "name": "Viaplay.dk",
    "logo_url": "https://www.tvsporten.dk/media/tvchannels/viaplay_dk_web.png"
   },
   {
    "name": "Norlys",
    "logo_url": "https://www.tvsporten.dk/media/tvchannels/norlys_100x60.jpg"
   }
  ]
 }
]