[
 {
  "match": "Canadas Grand Prix",
  "category": "Formel 1\n\t\t\t\t\t\t\t\t\t\t\t\tVBet Live odds",
  "time": "23:00",
  "date": "2025-06-13",
  "channels": [
   {
    "name": "TV3 Sport",
    "logo_url": "https://www.tvsporten.dk/media/tvchannels/tv3_sport_2web.png"
   },
   {
    "name": "Viaplay.dk",
    "logo_url": "https://www.tvsporten.dk/media/tvchannels/viaplay_dk_web.png"
   },
   {
    "name": "V Sport Live 3",
    "logo_url": "https://www.tvsporten.dk/media/tvchannels/v-sport-live-3100x60-1.jpg"
   },
   {
    "name": "Norlys",
    "logo_url": "https://www.tvsporten.dk/media/tvchannels/norlys_100x60.jpg"
   }
  ]
 }
]